codit/__init__.py
codit/__main__.py
codit/_internal/oidc/__init__.py
codit/_internal/oidc/ambient.py
codit-0.0.1.dist-info/LICENSE
codit-0.0.1.dist-info/WHEEL
codit-0.0.1.dist-info/METADATA
codit-0.0.1.dist-info/RECORD
