Metadata-Version: 2.1
Name: codit
Version: 0.0.1
Summary: A tool for generating OIDC identities
Requires-Python: >=3.7
Classifier: License :: OSI Approved :: Apache Software License
Classifier: Programming Language :: Python :: 3 :: Only
Classifier: Programming Language :: Python :: 3
Classifier: Programming Language :: Python :: 3.7
Classifier: Programming Language :: Python :: 3.8
Classifier: Programming Language :: Python :: 3.9
Classifier: Programming Language :: Python :: 3.10
Classifier: Programming Language :: Python :: 3.11
Classifier: Development Status :: 5 - Production/Stable
Classifier: Intended Audience :: Developers
Classifier: Topic :: Security
Classifier: Topic :: Security :: Cryptography
Requires-Dist: pydantic
Requires-Dist: requests
